tcrdist_rs-0.1.12.dist-info/METADATA
tcrdist_rs-0.1.12.dist-info/WHEEL
tcrdist_rs-0.1.12.dist-info/licenses/LICENSE
tcrdist_rs/__init__.py
tcrdist_rs/tcrdist_rs.abi3.so
tcrdist_rs-0.1.12.dist-info/RECORD
