Metadata-Version: 2.4
Name: tcrdist_rs
Version: 0.1.12
Classifier: Programming Language :: Rust
Classifier: Programming Language :: Python
Classifier: License :: OSI Approved :: MIT License
Classifier: Operating System :: OS Independent
License-File: LICENSE
Summary: Fast tcrdist routines between TCR sequences.
Keywords: tcrdist
Home-Page: https://github.com/zacmon/tcrdist_rs
Author: Zachary Montague
License: MIT
Requires-Python: >=3.7
Project-URL: repository, https://github.com/zacmon/tcrdist_rs
